{"eval/mean_reward": 0.0, "eval/mean_ep_length": 50.0, "time/total_timesteps": 1000}
{"eval/mean_reward": 0.0, "eval/mean_ep_length": 50.0, "time/total_timesteps": 2000}
{"time/iterations": 1, "rollout/ep_rew_mean": 0.3999999999999999, "rollout/ep_len_mean": 14.78, "time/fps": 0, "time/time_elapsed": -1683715399720192768, "time/total_timesteps": 2048}
{"train/learning_rate": 0.0003, "train/entropy_loss": -5.107125209271908, "train/policy_gradient_loss": -0.11049242935841903, "train/value_loss": 0.008859156149992487, "train/approx_kl": 0.030404124408960342, "train/clip_fraction": 0.527197265625, "train/loss": -0.14521142840385437, "train/explained_variance": -7.000672340393066, "train/n_updates": 20, "train/clip_range": 0.2, "eval/mean_reward": 0.0, "eval/mean_ep_length": 50.0, "time/total_timesteps": 3000}
{"eval/mean_reward": 0.0, "eval/mean_ep_length": 50.0, "time/total_timesteps": 4000}
{"time/iterations": 2, "rollout/ep_rew_mean": 0.3999999999999999, "rollout/ep_len_mean": 14.16, "time/fps": 0, "time/time_elapsed": -1683715399720192768, "time/total_timesteps": 4096}
{"train/learning_rate": 0.0003, "train/entropy_loss": -5.057232391834259, "train/policy_gradient_loss": -0.022405417647678404, "train/value_loss": 0.0006415032559289102, "train/approx_kl": 0.1924143135547638, "train/clip_fraction": 0.630810546875, "train/loss": -0.05124597251415253, "train/explained_variance": -0.0408402681350708, "train/n_updates": 40, "train/clip_range": 0.2, "eval/mean_reward": 0.0, "eval/mean_ep_length": 50.0, "time/total_timesteps": 5000}
{"eval/mean_reward": 0.0, "eval/mean_ep_length": 50.0, "time/total_timesteps": 6000}
{"time/iterations": 3, "rollout/ep_rew_mean": 0.3999999999999999, "rollout/ep_len_mean": 13.73, "time/fps": 0, "time/time_elapsed": -1683715399720192512, "time/total_timesteps": 6144}
{"train/learning_rate": 0.0003, "train/entropy_loss": -4.968313005566597, "train/policy_gradient_loss": -0.00932441066543106, "train/value_loss": 0.0007135547798952757, "train/approx_kl": 0.4436718821525574, "train/clip_fraction": 0.7388671875, "train/loss": -0.08712420612573624, "train/explained_variance": 0.05875658988952637, "train/n_updates": 60, "train/clip_range": 0.2, "eval/mean_reward": 0.3, "eval/mean_ep_length": 50.0, "time/total_timesteps": 7000}
{"eval/mean_reward": 0.3, "eval/mean_ep_length": 50.0, "time/total_timesteps": 8000}
{"time/iterations": 4, "rollout/ep_rew_mean": 0.3999999999999999, "rollout/ep_len_mean": 15.48, "time/fps": 0, "time/time_elapsed": -1683715399720192512, "time/total_timesteps": 8192}
{"train/learning_rate": 0.0003, "train/entropy_loss": -4.860788601636886, "train/policy_gradient_loss": 0.0064042537240311505, "train/value_loss": 0.0006983150212818146, "train/approx_kl": 0.903424859046936, "train/clip_fraction": 0.812158203125, "train/loss": -0.06282608956098557, "train/explained_variance": -0.29965972900390625, "train/n_updates": 80, "train/clip_range": 0.2, "eval/mean_reward": 0.3, "eval/mean_ep_length": 50.0, "time/total_timesteps": 9000}
{"eval/mean_reward": 0.3, "eval/mean_ep_length": 50.0, "time/total_timesteps": 10000}
{"time/iterations": 5, "rollout/ep_rew_mean": 0.3999999999999999, "rollout/ep_len_mean": 11.61, "time/fps": 0, "time/time_elapsed": -1683715399720192512, "time/total_timesteps": 10240}
{"train/learning_rate": 0.0003, "train/entropy_loss": -4.653989578783512, "train/policy_gradient_loss": -0.0049663443642202765, "train/value_loss": 0.000680697609186609, "train/approx_kl": 2.0902652740478516, "train/clip_fraction": 0.88115234375, "train/loss": -0.09142211824655533, "train/explained_variance": -0.3311772346496582, "train/n_updates": 100, "train/clip_range": 0.2, "eval/mean_reward": 0.3, "eval/mean_ep_length": 50.0, "time/total_timesteps": 11000}
{"eval/mean_reward": 0.3, "eval/mean_ep_length": 50.0, "time/total_timesteps": 12000}
{"time/iterations": 6, "rollout/ep_rew_mean": 0.3999999999999999, "rollout/ep_len_mean": 14.03, "time/fps": 0, "time/time_elapsed": -1683715399720192256, "time/total_timesteps": 12288}
{"train/learning_rate": 0.0003, "train/entropy_loss": -4.614401724934578, "train/policy_gradient_loss": -0.004803601975436322, "train/value_loss": 0.0006550191325459309, "train/approx_kl": 3.2643909454345703, "train/clip_fraction": 0.8802734375, "train/loss": -0.06931393593549728, "train/explained_variance": -0.47128748893737793, "train/n_updates": 120, "train/clip_range": 0.2, "eval/mean_reward": 0.4, "eval/mean_ep_length": 5.0, "time/total_timesteps": 13000}
{"eval/mean_reward": 0.4, "eval/mean_ep_length": 5.0, "time/total_timesteps": 14000}
{"time/iterations": 7, "rollout/ep_rew_mean": 0.3999999999999999, "rollout/ep_len_mean": 8.35, "time/fps": 0, "time/time_elapsed": -1683715399720192256, "time/total_timesteps": 14336}
{"train/learning_rate": 0.0003, "train/entropy_loss": -4.1275821179151535, "train/policy_gradient_loss": -0.02741317708569113, "train/value_loss": 0.00021474909829066746, "train/approx_kl": 13.536203384399414, "train/clip_fraction": 0.933447265625, "train/loss": -0.14440199732780457, "train/explained_variance": -0.5875749588012695, "train/n_updates": 140, "train/clip_range": 0.2, "eval/mean_reward": 0.4, "eval/mean_ep_length": 5.0, "time/total_timesteps": 15000}
{"eval/mean_reward": 0.4, "eval/mean_ep_length": 5.0, "time/total_timesteps": 16000}
{"time/iterations": 8, "rollout/ep_rew_mean": 0.3999999999999999, "rollout/ep_len_mean": 6.77, "time/fps": 0, "time/time_elapsed": -1683715399720192256, "time/total_timesteps": 16384}
{"train/learning_rate": 0.0003, "train/entropy_loss": -3.263120187073946, "train/policy_gradient_loss": 0.2455268615332898, "train/value_loss": 0.00010949684215688649, "train/approx_kl": 43.52020263671875, "train/clip_fraction": 0.959228515625, "train/loss": -0.10888447612524033, "train/explained_variance": -0.6455308198928833, "train/n_updates": 160, "train/clip_range": 0.2, "eval/mean_reward": 0.4, "eval/mean_ep_length": 5.0, "time/total_timesteps": 17000}
{"eval/mean_reward": 0.4, "eval/mean_ep_length": 5.0, "time/total_timesteps": 18000}
{"time/iterations": 9, "rollout/ep_rew_mean": 0.3999999999999999, "rollout/ep_len_mean": 7.49, "time/fps": 0, "time/time_elapsed": -1683715399720192000, "time/total_timesteps": 18432}
{"train/learning_rate": 0.0003, "train/entropy_loss": -2.4471143878996373, "train/policy_gradient_loss": -0.005933218979043886, "train/value_loss": 6.21861363242715e-05, "train/approx_kl": 30.465587615966797, "train/clip_fraction": 0.97470703125, "train/loss": -0.13170921802520752, "train/explained_variance": -0.8753402233123779, "train/n_updates": 180, "train/clip_range": 0.2, "eval/mean_reward": 0.4, "eval/mean_ep_length": 5.0, "time/total_timesteps": 19000}
{"eval/mean_reward": 0.4, "eval/mean_ep_length": 5.0, "time/total_timesteps": 20000}
{"time/iterations": 10, "rollout/ep_rew_mean": 0.3999999999999999, "rollout/ep_len_mean": 6.15, "time/fps": 0, "time/time_elapsed": -1683715399720192000, "time/total_timesteps": 20480}
{"train/learning_rate": 0.0003, "train/entropy_loss": -1.5649318039417266, "train/policy_gradient_loss": 0.050382923166034745, "train/value_loss": 0.00020015029101330128, "train/approx_kl": 107.2868423461914, "train/clip_fraction": 0.943017578125, "train/loss": -0.11737138032913208, "train/explained_variance": -0.886913537979126, "train/n_updates": 200, "train/clip_range": 0.2, "eval/mean_reward": 0.4, "eval/mean_ep_length": 5.0, "time/total_timesteps": 21000}
{"eval/mean_reward": 0.4, "eval/mean_ep_length": 5.0, "time/total_timesteps": 22000}
{"time/iterations": 11, "rollout/ep_rew_mean": 0.3999999999999999, "rollout/ep_len_mean": 5.8, "time/fps": 0, "time/time_elapsed": -1683715399720192000, "time/total_timesteps": 22528}
{"train/learning_rate": 0.0003, "train/entropy_loss": -0.9673641540110112, "train/policy_gradient_loss": -0.11944663678295911, "train/value_loss": 0.0002865643373866078, "train/approx_kl": 53.72810363769531, "train/clip_fraction": 0.820361328125, "train/loss": -0.13852651417255402, "train/explained_variance": -0.9411674737930298, "train/n_updates": 220, "train/clip_range": 0.2, "eval/mean_reward": 0.4, "eval/mean_ep_length": 5.0, "time/total_timesteps": 23000}
{"eval/mean_reward": 0.4, "eval/mean_ep_length": 5.0, "time/total_timesteps": 24000}
{"time/iterations": 12, "rollout/ep_rew_mean": 0.3999999999999999, "rollout/ep_len_mean": 5.19, "time/fps": 0, "time/time_elapsed": -1683715399720191744, "time/total_timesteps": 24576}
{"train/learning_rate": 0.0003, "train/entropy_loss": -0.6870234534144402, "train/policy_gradient_loss": -0.10827071295352653, "train/value_loss": 0.0006195048330795317, "train/approx_kl": 25.954593658447266, "train/clip_fraction": 0.704736328125, "train/loss": -0.10696204751729965, "train/explained_variance": -1.0297701358795166, "train/n_updates": 240, "train/clip_range": 0.2, "eval/mean_reward": 0.4, "eval/mean_ep_length": 5.0, "time/total_timesteps": 25000}
{"eval/mean_reward": 0.4, "eval/mean_ep_length": 5.0, "time/total_timesteps": 26000}
{"time/iterations": 13, "rollout/ep_rew_mean": 0.3999999999999999, "rollout/ep_len_mean": 5.21, "time/fps": 0, "time/time_elapsed": -1683715399720191744, "time/total_timesteps": 26624}
{"train/learning_rate": 0.0003, "train/entropy_loss": -0.4648014330305159, "train/policy_gradient_loss": -0.11120702009648084, "train/value_loss": 0.00015188786106250517, "train/approx_kl": 26.95027732849121, "train/clip_fraction": 0.641357421875, "train/loss": -0.08385232836008072, "train/explained_variance": -0.9775805473327637, "train/n_updates": 260, "train/clip_range": 0.2, "eval/mean_reward": 0.4, "eval/mean_ep_length": 5.0, "time/total_timesteps": 27000}
{"eval/mean_reward": 0.4, "eval/mean_ep_length": 5.0, "time/total_timesteps": 28000}
{"time/iterations": 14, "rollout/ep_rew_mean": 0.3999999999999999, "rollout/ep_len_mean": 5.37, "time/fps": 0, "time/time_elapsed": -1683715399720191744, "time/total_timesteps": 28672}
{"train/learning_rate": 0.0003, "train/entropy_loss": -0.34083956596441567, "train/policy_gradient_loss": -0.10556466646958143, "train/value_loss": 0.000456534504468209, "train/approx_kl": 19.479171752929688, "train/clip_fraction": 0.45322265625, "train/loss": -0.10667407512664795, "train/explained_variance": -1.0189549922943115, "train/n_updates": 280, "train/clip_range": 0.2, "eval/mean_reward": 0.4, "eval/mean_ep_length": 5.0, "time/total_timesteps": 29000}
{"eval/mean_reward": 0.4, "eval/mean_ep_length": 5.0, "time/total_timesteps": 30000}
{"time/iterations": 15, "rollout/ep_rew_mean": 0.3999999999999999, "rollout/ep_len_mean": 5.42, "time/fps": 0, "time/time_elapsed": -1683715399720191744, "time/total_timesteps": 30720}
{"train/learning_rate": 0.0003, "train/entropy_loss": -0.298044260032475, "train/policy_gradient_loss": -0.09324384973151609, "train/value_loss": 9.266638745870636e-05, "train/approx_kl": 20.449256896972656, "train/clip_fraction": 0.46826171875, "train/loss": -0.09537501633167267, "train/explained_variance": -0.9654639959335327, "train/n_updates": 300, "train/clip_range": 0.2, "eval/mean_reward": 0.4, "eval/mean_ep_length": 5.0, "time/total_timesteps": 31000}
{"eval/mean_reward": 0.4, "eval/mean_ep_length": 5.0, "time/total_timesteps": 32000}
{"time/iterations": 16, "rollout/ep_rew_mean": 0.3999999999999999, "rollout/ep_len_mean": 5.11, "time/fps": 0, "time/time_elapsed": -1683715399720191488, "time/total_timesteps": 32768}
{"train/learning_rate": 0.0003, "train/entropy_loss": -0.28855768060311676, "train/policy_gradient_loss": -0.08158868413884193, "train/value_loss": 0.00030302913677644484, "train/approx_kl": 40.153594970703125, "train/clip_fraction": 0.485107421875, "train/loss": -0.07164900004863739, "train/explained_variance": -0.970551609992981, "train/n_updates": 320, "train/clip_range": 0.2, "eval/mean_reward": 0.4, "eval/mean_ep_length": 5.0, "time/total_timesteps": 33000}
{"eval/mean_reward": 0.4, "eval/mean_ep_length": 5.0, "time/total_timesteps": 34000}
{"time/iterations": 17, "rollout/ep_rew_mean": 0.3999999999999999, "rollout/ep_len_mean": 5.13, "time/fps": 0, "time/time_elapsed": -1683715399720191488, "time/total_timesteps": 34816}
{"train/learning_rate": 0.0003, "train/entropy_loss": -0.26820645104162394, "train/policy_gradient_loss": -0.062384255393408236, "train/value_loss": 5.696500193046461e-05, "train/approx_kl": 18.249034881591797, "train/clip_fraction": 0.49326171875, "train/loss": -0.04361290857195854, "train/explained_variance": -1.0600697994232178, "train/n_updates": 340, "train/clip_range": 0.2, "eval/mean_reward": 0.4, "eval/mean_ep_length": 5.0, "time/total_timesteps": 35000}
{"eval/mean_reward": 0.4, "eval/mean_ep_length": 5.0, "time/total_timesteps": 36000}
{"time/iterations": 18, "rollout/ep_rew_mean": 0.3999999999999999, "rollout/ep_len_mean": 5.12, "time/fps": 0, "time/time_elapsed": -1683715399720191488, "time/total_timesteps": 36864}
{"train/learning_rate": 0.0003, "train/entropy_loss": -0.28927975744009016, "train/policy_gradient_loss": 0.11410466771922075, "train/value_loss": 0.0006251823760521802, "train/approx_kl": 24.219127655029297, "train/clip_fraction": 0.51416015625, "train/loss": -0.057778049260377884, "train/explained_variance": -1.0222327709197998, "train/n_updates": 360, "train/clip_range": 0.2, "eval/mean_reward": 0.4, "eval/mean_ep_length": 5.0, "time/total_timesteps": 37000}
{"eval/mean_reward": 0.4, "eval/mean_ep_length": 5.0, "time/total_timesteps": 38000}
{"time/iterations": 19, "rollout/ep_rew_mean": 0.3999999999999999, "rollout/ep_len_mean": 5.07, "time/fps": 0, "time/time_elapsed": -1683715399720191232, "time/total_timesteps": 38912}
{"train/learning_rate": 0.0003, "train/entropy_loss": -0.2912841096986085, "train/policy_gradient_loss": -0.09884090484119952, "train/value_loss": 0.00026249967239380114, "train/approx_kl": 21.07903480529785, "train/clip_fraction": 0.421875, "train/loss": -0.10458473116159439, "train/explained_variance": -1.1434240341186523, "train/n_updates": 380, "train/clip_range": 0.2, "eval/mean_reward": 0.4, "eval/mean_ep_length": 5.0, "time/total_timesteps": 39000}
{"eval/mean_reward": 0.4, "eval/mean_ep_length": 5.0, "time/total_timesteps": 40000}
{"time/iterations": 20, "rollout/ep_rew_mean": 0.3999999999999999, "rollout/ep_len_mean": 5.07, "time/fps": 0, "time/time_elapsed": -1683715399720191232, "time/total_timesteps": 40960}
{"train/learning_rate": 0.0003, "train/entropy_loss": -0.2822549899574369, "train/policy_gradient_loss": -0.10318518341518938, "train/value_loss": 0.0002179801481695165, "train/approx_kl": 14.0283203125, "train/clip_fraction": 0.41162109375, "train/loss": -0.11599688231945038, "train/explained_variance": -0.9874308109283447, "train/n_updates": 400, "train/clip_range": 0.2, "eval/mean_reward": 0.4, "eval/mean_ep_length": 5.0, "time/total_timesteps": 41000}
{"eval/mean_reward": 0.4, "eval/mean_ep_length": 5.0, "time/total_timesteps": 42000}
{"eval/mean_reward": 0.4, "eval/mean_ep_length": 5.0, "time/total_timesteps": 43000}
{"time/iterations": 21, "rollout/ep_rew_mean": 0.3999999999999999, "rollout/ep_len_mean": 5.05, "time/fps": 0, "time/time_elapsed": -1683715399720191232, "time/total_timesteps": 43008}
{"train/learning_rate": 0.0003, "train/entropy_loss": -0.33957820078358053, "train/policy_gradient_loss": -0.10150430791545659, "train/value_loss": 0.0004199853099365214, "train/approx_kl": 30.662635803222656, "train/clip_fraction": 0.4208984375, "train/loss": -0.10620567202568054, "train/explained_variance": -1.151500940322876, "train/n_updates": 420, "train/clip_range": 0.2, "eval/mean_reward": 0.4, "eval/mean_ep_length": 5.0, "time/total_timesteps": 44000}
{"eval/mean_reward": 0.4, "eval/mean_ep_length": 5.0, "time/total_timesteps": 45000}
{"time/iterations": 22, "rollout/ep_rew_mean": 0.3999999999999999, "rollout/ep_len_mean": 5.03, "time/fps": 0, "time/time_elapsed": -1683715399720190976, "time/total_timesteps": 45056}
{"train/learning_rate": 0.0003, "train/entropy_loss": -0.34642770546488466, "train/policy_gradient_loss": -0.1025061372667551, "train/value_loss": 0.00026521069389957576, "train/approx_kl": 35.18657684326172, "train/clip_fraction": 0.4150390625, "train/loss": -0.0972667783498764, "train/explained_variance": -0.982375979423523, "train/n_updates": 440, "train/clip_range": 0.2, "eval/mean_reward": 0.4, "eval/mean_ep_length": 5.0, "time/total_timesteps": 46000}
{"eval/mean_reward": 0.4, "eval/mean_ep_length": 5.0, "time/total_timesteps": 47000}
{"time/iterations": 23, "rollout/ep_rew_mean": 0.3999999999999999, "rollout/ep_len_mean": 5.06, "time/fps": 0, "time/time_elapsed": -1683715399720190976, "time/total_timesteps": 47104}
{"train/learning_rate": 0.0003, "train/entropy_loss": -0.3390621320344508, "train/policy_gradient_loss": -0.10422387975268066, "train/value_loss": 0.0005961595910974893, "train/approx_kl": 14.386091232299805, "train/clip_fraction": 0.4169921875, "train/loss": -0.11256328970193863, "train/explained_variance": -0.9728035926818848, "train/n_updates": 460, "train/clip_range": 0.2, "eval/mean_reward": 0.4, "eval/mean_ep_length": 5.0, "time/total_timesteps": 48000}
{"eval/mean_reward": 0.4, "eval/mean_ep_length": 5.0, "time/total_timesteps": 49000}
{"time/iterations": 24, "rollout/ep_rew_mean": 0.3999999999999999, "rollout/ep_len_mean": 5.04, "time/fps": 0, "time/time_elapsed": -1683715399720190976, "time/total_timesteps": 49152}
{"train/learning_rate": 0.0003, "train/entropy_loss": -0.33522218530997633, "train/policy_gradient_loss": -0.1010699008940719, "train/value_loss": 0.00045862938818999057, "train/approx_kl": 53.644447326660156, "train/clip_fraction": 0.41650390625, "train/loss": -0.1024370789527893, "train/explained_variance": -1.1097476482391357, "train/n_updates": 480, "train/clip_range": 0.2, "eval/mean_reward": 0.4, "eval/mean_ep_length": 5.0, "time/total_timesteps": 50000}
{"eval/mean_reward": 0.4, "eval/mean_ep_length": 5.0, "time/total_timesteps": 51000}
{"time/iterations": 25, "rollout/ep_rew_mean": 0.3999999999999999, "rollout/ep_len_mean": 5.03, "time/fps": 0, "time/time_elapsed": -1683715399720190976, "time/total_timesteps": 51200}
